{
  "name": "tabs",
  "type": "registry:ui",
  "description": "Segmented navigation with an animated indicator.",
  "registryDependencies": [
    "cn",
    "text"
  ],
  "dependencies": [
    "react-native-reanimated",
    "tailwind-variants"
  ],
  "optionalDependencies": [],
  "files": [
    {
      "path": "ui/tabs.tsx",
      "type": "registry:ui",
      "content": "/**\n * Tabs — segmented navigation between panels.\n *\n * The active tab is marked by one indicator that slides between measured\n * trigger positions rather than by a style on each trigger. That is what makes\n * the movement continuous: there is a single thing travelling, so a switch two\n * tabs away reads as one gesture instead of two states swapping.\n *\n * ```tsx\n * <Tabs defaultValue=\"account\">\n *   <Tabs.List>\n *     <Tabs.Trigger value=\"account\">Account</Tabs.Trigger>\n *     <Tabs.Trigger value=\"team\" badge={<Badge>3</Badge>}>Team</Tabs.Trigger>\n *   </Tabs.List>\n *   <Tabs.Content value=\"account\">…</Tabs.Content>\n * </Tabs>\n * ```\n */\nimport {\n  createContext,\n  useCallback,\n  useContext,\n  useEffect,\n  useMemo,\n  useRef,\n  useState,\n  type ReactNode,\n} from 'react';\nimport {\n  Pressable,\n  ScrollView,\n  View,\n  type LayoutChangeEvent,\n  type ViewProps,\n} from 'react-native';\nimport Animated, {\n  FadeIn,\n  useAnimatedStyle,\n  useSharedValue,\n  withSpring,\n} from 'react-native-reanimated';\nimport { tv } from 'tailwind-variants';\nimport { Text } from '@/components/ui/text';\nimport { cn } from '@/lib/cn';\n\nconst SPRING = { damping: 24, stiffness: 300, mass: 0.7 } as const;\n\nexport type TabsVariant = 'segmented' | 'underline' | 'pill';\n\nconst tabsVariants = tv({\n  slots: {\n    list: 'flex-row',\n    indicator: 'absolute left-0',\n    trigger: 'items-center justify-center',\n    label: '',\n  },\n  variants: {\n    variant: {\n      // A raised chip travelling inside a recessed track.\n      segmented: {\n        list: 'rounded-lg bg-muted p-1',\n        indicator: 'bottom-1 top-1 rounded-md bg-popover shadow-sm',\n        trigger: 'rounded-md py-1.5',\n      },\n      // No track at all — the indicator is a rule under the active tab, and\n      // the row sits on a hairline so inactive tabs still have a baseline.\n      underline: {\n        list: 'gap-1 border-b border-border',\n        indicator: '-bottom-px h-0.5 rounded-full bg-foreground',\n        trigger: 'py-2.5',\n      },\n      // Filled chip on the page rather than in a track; the active label\n      // inverts against it.\n      pill: {\n        list: 'gap-1',\n        indicator: 'bottom-0 top-0 rounded-full bg-primary',\n        trigger: 'rounded-full py-2',\n      },\n    },\n    active: {\n      true: { label: 'text-foreground' },\n      false: { label: 'text-muted-foreground' },\n    },\n    disabled: {\n      true: { trigger: 'opacity-[0.44]' },\n    },\n    /** Intrinsic width in a scroller, equal shares when the row is fixed. */\n    scrollable: {\n      true: { trigger: 'px-4' },\n      false: { trigger: 'flex-1' },\n    },\n  },\n  compoundVariants: [\n    { variant: 'pill', active: true, class: { label: 'text-primary-foreground' } },\n  ],\n  defaultVariants: {\n    variant: 'segmented',\n    scrollable: false,\n  },\n});\n\ninterface TabLayout {\n  x: number;\n  width: number;\n}\n\ninterface TabsContextValue {\n  value: string;\n  setValue: (value: string) => void;\n  registerLayout: (value: string, layout: TabLayout) => void;\n  layouts: Record<string, TabLayout>;\n  variant: TabsVariant;\n  scrollable: boolean;\n  setScrollable: (scrollable: boolean) => void;\n  keepMounted: boolean;\n}\n\nconst TabsContext = createContext<TabsContextValue | null>(null);\n\nfunction useTabs(component: string): TabsContextValue {\n  const context = useContext(TabsContext);\n  if (!context) {\n    throw new Error(`${component} must be used within a <Tabs>`);\n  }\n  return context;\n}\n\nexport interface TabsProps extends ViewProps {\n  className?: string;\n  value?: string;\n  onValueChange?: (value: string) => void;\n  defaultValue: string;\n  /**\n   * `segmented` is a chip travelling inside a recessed track, `underline` is a\n   * rule under the active tab, `pill` is a filled chip on the page.\n   */\n  variant?: TabsVariant;\n  /**\n   * Keep inactive panels mounted and hidden instead of unmounting them, so a\n   * scroll position or a half-filled form survives a switch away and back.\n   * Costs the render of every panel up front.\n   */\n  keepMounted?: boolean;\n  children: ReactNode;\n}\n\nfunction TabsRoot({\n  className,\n  value,\n  onValueChange,\n  defaultValue,\n  variant = 'segmented',\n  keepMounted = false,\n  children,\n  ...props\n}: TabsProps) {\n  const [internalValue, setInternalValue] = useState(defaultValue);\n  const [layouts, setLayouts] = useState<Record<string, TabLayout>>({});\n  // Published by the List rather than the root, because it is the List that\n  // decides whether it scrolls — but the Triggers below it need to know.\n  const [scrollable, setScrollable] = useState(false);\n  const isControlled = value !== undefined;\n  const resolvedValue = isControlled ? value : internalValue;\n\n  const setValue = useCallback(\n    (next: string) => {\n      if (!isControlled) setInternalValue(next);\n      onValueChange?.(next);\n    },\n    [isControlled, onValueChange]\n  );\n\n  const registerLayout = useCallback((tab: string, layout: TabLayout) => {\n    setLayouts((current) => {\n      const existing = current[tab];\n      if (existing && existing.x === layout.x && existing.width === layout.width) {\n        return current;\n      }\n      return { ...current, [tab]: layout };\n    });\n  }, []);\n\n  const context = useMemo(\n    () => ({\n      value: resolvedValue,\n      setValue,\n      registerLayout,\n      layouts,\n      variant,\n      scrollable,\n      setScrollable,\n      keepMounted,\n    }),\n    [resolvedValue, setValue, registerLayout, layouts, variant, scrollable, keepMounted]\n  );\n\n  return (\n    <TabsContext.Provider value={context}>\n      <View className={cn('gap-3', className)} {...props}>\n        {children}\n      </View>\n    </TabsContext.Provider>\n  );\n}\n\nfunction TabsIndicator() {\n  const { value, layouts, variant } = useTabs('Tabs.List');\n  const x = useSharedValue(0);\n  const width = useSharedValue(0);\n  const initialized = useSharedValue(0);\n\n  const layout = layouts[value];\n  const { indicator } = tabsVariants({ variant });\n\n  // In an effect, not the render body: touching a shared value during render\n  // is a Reanimated strict-mode violation, and the write can be lost or\n  // duplicated when React re-renders.\n  useEffect(() => {\n    if (!layout) return;\n\n    if (initialized.value === 0) {\n      // First measurement snaps into place; there is nothing to animate from.\n      x.value = layout.x;\n      width.value = layout.width;\n      initialized.value = 1;\n    } else {\n      x.value = withSpring(layout.x, SPRING);\n      width.value = withSpring(layout.width, SPRING);\n    }\n  }, [layout?.x, layout?.width, x, width, initialized, layout]);\n\n  const style = useAnimatedStyle(() => ({\n    opacity: initialized.value,\n    transform: [{ translateX: x.value }],\n    width: width.value,\n  }));\n\n  return <Animated.View style={style} className={indicator()} />;\n}\n\nexport interface TabsListProps extends ViewProps {\n  className?: string;\n  /**\n   * Lay the triggers out at their natural widths inside a horizontal scroller\n   * instead of splitting the row between them. For more tabs than fit — which\n   * a fixed row answers by crushing every label.\n   */\n  scrollable?: boolean;\n  children: ReactNode;\n}\n\nfunction TabsList({ className, scrollable = false, children, ...props }: TabsListProps) {\n  const { variant, setScrollable, value, layouts } = useTabs('Tabs.List');\n  const { list } = tabsVariants({ variant });\n  const scroller = useRef<ScrollView>(null);\n\n  useEffect(() => {\n    setScrollable(scrollable);\n  }, [scrollable, setScrollable]);\n\n  // Bring the active tab into view when it changes from elsewhere — a\n  // controlled switch, or a swipe on the panel below.\n  const activeLayout = layouts[value];\n  useEffect(() => {\n    if (!scrollable || !activeLayout) return;\n    scroller.current?.scrollTo({\n      // Land the tab a little in from the edge rather than flush against it,\n      // so it does not read as the last one in the row.\n      x: Math.max(activeLayout.x - 24, 0),\n      animated: true,\n    });\n  }, [scrollable, activeLayout?.x, activeLayout]);\n\n  const row = (\n    <View accessibilityRole=\"tablist\" className={cn(list(), className)} {...props}>\n      <TabsIndicator />\n      {children}\n    </View>\n  );\n\n  if (!scrollable) return row;\n\n  return (\n    <ScrollView\n      ref={scroller}\n      horizontal\n      showsHorizontalScrollIndicator={false}\n      // The row measures itself, and the indicator is positioned against it,\n      // so the scroller must not stretch it to the viewport width.\n      contentContainerStyle={{ flexGrow: 0 }}\n    >\n      {row}\n    </ScrollView>\n  );\n}\n\nexport interface TabsTriggerProps {\n  className?: string;\n  value: string;\n  /** Rendered before the label. */\n  icon?: ReactNode;\n  /** Rendered after the label — a count, a dot, a status. */\n  badge?: ReactNode;\n  /** Unselectable, dimmed, and announced as disabled. */\n  disabled?: boolean;\n  children: ReactNode;\n}\n\nfunction TabsTrigger({\n  className,\n  value,\n  icon,\n  badge,\n  disabled = false,\n  children,\n}: TabsTriggerProps) {\n  const context = useTabs('Tabs.Trigger');\n  const active = context.value === value;\n  const slots = tabsVariants({\n    variant: context.variant,\n    active,\n    disabled,\n    scrollable: context.scrollable,\n  });\n\n  const handleLayout = useCallback(\n    (event: LayoutChangeEvent) => {\n      const { x, width } = event.nativeEvent.layout;\n      context.registerLayout(value, { x, width });\n    },\n    [context, value]\n  );\n\n  return (\n    <Pressable\n      accessibilityRole=\"tab\"\n      accessibilityState={{ selected: active, disabled }}\n      disabled={disabled}\n      onPress={() => context.setValue(value)}\n      onLayout={handleLayout}\n      className={cn(slots.trigger(), (icon || badge) && 'flex-row gap-1.5', className)}\n    >\n      {icon}\n      {typeof children === 'string' ? (\n        <Text size=\"sm\" weight=\"medium\" className={slots.label()}>\n          {children}\n        </Text>\n      ) : (\n        children\n      )}\n      {badge}\n    </Pressable>\n  );\n}\n\nexport interface TabsContentProps extends ViewProps {\n  className?: string;\n  value: string;\n  children: ReactNode;\n}\n\nfunction TabsContent({ className, value, children, style, ...props }: TabsContentProps) {\n  const context = useTabs('Tabs.Content');\n  const active = context.value === value;\n\n  if (!active && !context.keepMounted) return null;\n\n  /*\n   * Hidden rather than unmounted under `keepMounted`, and hidden thoroughly:\n   * `display: none` takes it out of layout, and the accessibility props take\n   * it out of the reading order too. A screen reader walking through three\n   * panels of a tab set it cannot see is worse than no tabs at all.\n   */\n  return (\n    <Animated.View\n      // Only worth animating when the panel is genuinely arriving. A kept\n      // panel is already there; fading it in every time it is revealed would\n      // undo the point of keeping it.\n      entering={context.keepMounted ? undefined : FadeIn.duration(150)}\n      style={[!active && { display: 'none' }, style]}\n      pointerEvents={active ? 'auto' : 'none'}\n      accessibilityElementsHidden={!active}\n      importantForAccessibility={active ? 'auto' : 'no-hide-descendants'}\n      className={className}\n      {...props}\n    >\n      {children}\n    </Animated.View>\n  );\n}\n\nexport const Tabs = Object.assign(TabsRoot, {\n  List: TabsList,\n  Trigger: TabsTrigger,\n  Content: TabsContent,\n});\n"
    }
  ]
}
